LICENSE
README.txt
setup.py
examples/models.py
examples/tests.py
examples/tests2.py
noseonalchemist/__init__.py
noseonalchemist.egg-info/PKG-INFO
noseonalchemist.egg-info/SOURCES.txt
noseonalchemist.egg-info/dependency_links.txt
noseonalchemist.egg-info/entry_points.txt
noseonalchemist.egg-info/requires.txt
noseonalchemist.egg-info/top_level.txt