Metadata-Version: 1.0
Name: noseonalchemist
Version: 0.1
Summary: nose plugin for reporting about commit counts on SQLAlchemy
Home-page: https://github.com/aodag/noseonalchemist
Author: Atsushi Odagiri
Author-email: aodagx@gmail.com
License: MIT
Platform: UNKNOWN
Classifier: Development Status :: 4 - Beta
Classifier: Environment :: Plugins
Classifier: Topic :: Software Development :: Testing
Classifier: Intended Audience :: Developers
Classifier: License :: OSI Approved :: MIT License
